retvec/__init__.py
retvec/tf/__init__.py
retvec/tf/utils.py
retvec/tf/dataset/__init__.py
retvec/tf/dataset/io.py
retvec/tf/layers/__init__.py
retvec/tf/layers/binarizer.py
retvec/tf/layers/embedding.py
retvec/tf/layers/integerizer.py
retvec/tf/layers/tokenizer.py
retvec/tf/models/__init__.py
retvec/tf/models/gau.py
retvec/tf/models/layers.py
retvec/tf/models/outputs.py
retvec/tf/models/positional_embeddings.py
retvec/tf/models/retvec_base.py
retvec/tf/models/retvec_large.py
retvec/tf/optimizers/__init__.py
retvec/tf/optimizers/warmup_cosine_decay.py
retvec-1.0.1.dist-info/LICENSE
retvec-1.0.1.dist-info/METADATA
retvec-1.0.1.dist-info/WHEEL
retvec-1.0.1.dist-info/top_level.txt
retvec-1.0.1.dist-info/RECORD
