Metadata-Version: 2.1
Name: retvec
Version: 1.0.1
Summary: Resilient and Efficient Text Vectorizer
Home-page: https://github.com/google-research/retvec
Author: Google
Author-email: retvec@google.com
License: Apache License 2.0
Platform: UNKNOWN
Classifier: Development Status :: 3 - Alpha
Classifier: Environment :: Console
Classifier: License :: OSI Approved :: Apache Software License
Classifier: Intended Audience :: Science/Research
Classifier: Programming Language :: Python :: 3
Classifier: Topic :: Scientific/Engineering :: Artificial Intelligence
License-File: LICENSE
Provides-Extra: dev
Requires-Dist: datasets ; extra == 'dev'
Requires-Dist: tokenizers ; extra == 'dev'
Requires-Dist: tensorflow-addons ; extra == 'dev'
Requires-Dist: google-cloud-storage ; extra == 'dev'
Requires-Dist: wandb ; extra == 'dev'
Requires-Dist: mypy ; extra == 'dev'
Requires-Dist: pytest ; extra == 'dev'
Requires-Dist: flake8 ; extra == 'dev'
Requires-Dist: pytest-cov ; extra == 'dev'
Requires-Dist: twine ; extra == 'dev'
Requires-Dist: tabulate ; extra == 'dev'
Requires-Dist: numpy ; extra == 'dev'
Requires-Dist: tqdm ; extra == 'dev'
Requires-Dist: tensorflow-similarity ; extra == 'dev'
Requires-Dist: black ; extra == 'dev'
Requires-Dist: isort ; extra == 'dev'
Provides-Extra: tensorflow
Requires-Dist: tensorflow >=2.6 ; extra == 'tensorflow'
